emails/__init__.py
emails/django_.py
emails/exc.py
emails/message.py
emails/signers.py
emails/transformer.py
emails/utils.py
emails/compat/__init__.py
emails/compat/_urlparse.py
emails/compat/ordereddict.py
emails/compat/orderedset.py
emails/django/__init__.py
emails/loader/__init__.py
emails/loader/helpers.py
emails/loader/local_store.py
emails/store/__init__.py
emails/store/file.py
emails/store/store.py
emails/backend/__init__.py
emails/backend/factory.py
emails/backend/response.py
emails/backend/smtp/__init__.py
emails/backend/smtp/backend.py
emails/backend/smtp/client.py
emails/backend/smtp/exceptions.py
emails/template/__init__.py
emails/template/base.py
emails/template/jinja_template.py
emails/template/mako_template.py
emails/packages/__init__.py
emails/packages/dkim/__init__.py
emails/packages/dkim/__main__.py
emails/packages/dkim/asn1.py
emails/packages/dkim/canonicalization.py
emails/packages/dkim/crypto.py
emails/packages/dkim/dnsplug.py
emails/packages/dkim/util.py
emails-0.5.15.data/scripts/make_rfc822.py
emails-0.5.15.dist-info/top_level.txt
emails-0.5.15.dist-info/METADATA
emails-0.5.15.dist-info/DESCRIPTION.rst
emails-0.5.15.dist-info/metadata.json
emails-0.5.15.dist-info/WHEEL
emails-0.5.15.dist-info/RECORD
