Metadata-Version: 1.1
Name: emails
Version: 0.5.15
Summary: Modern python library for emails.
Home-page: https://github.com/lavr/python-emails
Author: Sergey Lavrinenko
Author-email: s@lavr.me
License: Copyright 2013-2015 Sergey Lavrinenko
